[
  {
    "Full Product Name": "Dell Pro 14 Plus Portable Monitor - P1425",
    "Model": "P1425",
    "Brand": "DELL",
    "Brief Naming": "DELL Pro Series LED Monitor",
    "Size": "14\"",
    "Resolution": "1920 x 1200 WUXGA",
    "Response Time": "7.0ms",
    "Refresh Rate": "",
    "Compatible Ports": "2 USB-C, 1 DisplayPort",
    "Warranty": "3 Years"
  },
  {
    "Full Product Name": "Dell Pro 24 Plus Touch USB-C Hub Monitor - P2424HT",
    "Model": "P2424HT",
    "Brand": "DELL",
    "Brief Naming": "DELL Pro Series LED Monitor",
    "Size": "24\"",
    "Resolution": "1920 x 1200 WUXGA",
    "Response Time": "5.0ms",
    "Refresh Rate": "",
    "Compatible Ports": "1 HDMI, 1 DisplayPort, 2 USB-C, Ethernet",
    "Warranty": "3 Years"
  },
  {
    "Full Product Name": "Dell 27 QHD Monitor - SE2726D",
    "Model": "SE2726D",
    "Brand": "DELL",
    "Brief Naming": "DELL SE Series LED Monitor",
    "Size": "27\"",
    "Resolution": "2560 x 1440 QHD",
    "Response Time": "1.0ms",
    "Refresh Rate": "144Hz",
    "Compatible Ports": "2 HDMI, 1 DisplayPort",
    "Warranty": "3 Years"
  },
  {
    "Full Product Name": "Dell Pro P 24 USB-C Hub Webcam Monitor - P2426HEV",
    "Model": "P2426HE",
    "Brand": "DELL",
    "Brief Naming": "DELL Pro Series LED Monitor",
    "Size": "24\"",
    "Resolution": "",
    "Response Time": "5.0ms",
    "Refresh Rate": "120Hz",
    "Compatible Ports": "1 HDMI, 2 DisplayPort (1 in, 1 out), USB-C",
    "Warranty": "3 Years"
  },
  {
    "Full Product Name": "Dell Pro P 24 USB-C Hub Conferencing Monitor - P2426HEB",
    "Model": "P2426HE",
    "Brand": "DELL",
    "Brief Naming": "DELL Pro Series LED Monitor",
    "Size": "24\"",
    "Resolution": "",
    "Response Time": "5.0ms",
    "Refresh Rate": "",
    "Compatible Ports": "1 HDMI, 2 DisplayPort (1 in, 1 out), USB-C",
    "Warranty": "3 Years"
  },
  {
    "Full Product Name": "Dell Pro P 27 USB-C Hub Webcam Monitor - P2726DEV",
    "Model": "P2726DE",
    "Brand": "DELL",
    "Brief Naming": "DELL Pro Series LED Monitor",
    "Size": "27\"",
    "Resolution": "",
    "Response Time": "5.0ms",
    "Refresh Rate": "100Hz",
    "Compatible Ports": "1 HDMI, 2 DisplayPort (1 in, 1 out), USB-C",
    "Warranty": "3 Years"
  },
  {
    "Full Product Name": "Dell Pro P 27 USB-C Hub Conferencing Monitor - P2726DEB",
    "Model": "P2726DE",
    "Brand": "DELL",
    "Brief Naming": "DELL Pro Series LED Monitor",
    "Size": "27\"",
    "Resolution": "",
    "Response Time": "5.0ms",
    "Refresh Rate": "",
    "Compatible Ports": "1 HDMI, 2 DisplayPort (1 in, 1 out), USB-C",
    "Warranty": "3 Years"
  },
  {
    "Full Product Name": "Dell Pro P 34 USB-C Hub Webcam Monitor - P3426WEV",
    "Model": "P3426WE",
    "Brand": "DELL",
    "Brief Naming": "DELL Pro Series LED Monitor",
    "Size": "34\"",
    "Resolution": "",
    "Response Time": "5.0ms",
    "Refresh Rate": "100Hz",
    "Compatible Ports": "1 HDMI, 2 DisplayPort (1 in, 1 out), USB-C",
    "Warranty": "3 Years"
  },
  {
    "Full Product Name": "Dell Pro P 34 USB-C Hub Conferencing Monitor - P3426WEB",
    "Model": "P3426WE",
    "Brand": "DELL",
    "Brief Naming": "DELL Pro Series LED Monitor",
    "Size": "34\"",
    "Resolution": "",
    "Response Time": "5.0ms",
    "Refresh Rate": "100Hz",
    "Compatible Ports": "1 HDMI, 2 DisplayPort (1 in, 1 out), USB-C",
    "Warranty": "3 Years"
  },
  {
    "Full Product Name": "Dell UltraSharp 32 4K QD-OLED Monitor - U3226Q",
    "Model": "U3226Q",
    "Brand": "DELL",
    "Brief Naming": "Dell UltraSharp Series LED Monitor",
    "Size": "32\"",
    "Resolution": "3840 x 2160 4K UHD",
    "Response Time": "",
    "Refresh Rate": "120Hz",
    "Compatible Ports": "DisplayPort, HDMI, USB-C, Thunderbolt, Ethernet",
    "Warranty": "3 Years"
  },
  {
    "Full Product Name": "Dell Pro 24 Plus Monitor - P2425H",
    "Model": "P2425H",
    "Brand": "DELL",
    "Brief Naming": "DELL Pro Series LED Monitor",
    "Size": "24\"",
    "Resolution": "1920 x 1200 WUXGA",
    "Response Time": "5.0ms",
    "Refresh Rate": "100Hz",
    "Compatible Ports": "1 HDMI, 1 VGA, 1 USB-C",
    "Warranty": "3 Years"
  },
  {
    "Full Product Name": "Dell 27 Plus 4K USB-C Monitor - S2725QC",
    "Model": "S2725QC",
    "Brand": "DELL",
    "Brief Naming": "DELL S Series LED Monitor",
    "Size": "27\"",
    "Resolution": "3840 x 2160 4K UHD",
    "Response Time": "5.0ms",
    "Refresh Rate": "120Hz",
    "Compatible Ports": "1 HDMI, 1 DisplayPort, 1 USB-C",
    "Warranty": "3 Years"
  },
  {
    "Full Product Name": "Alienware 32 4K QD-OLED Gaming Monitor - AW3225QF",
    "Model": "AW3225QF",
    "Brand": "DELL",
    "Brief Naming": "Dell Alienware Series LED Monitor",
    "Size": "32\"",
    "Resolution": "2560 x 1440 QHD",
    "Response Time": "",
    "Refresh Rate": "240Hz",
    "Compatible Ports": "DisplayPort, HDMI, USB-C, Thunderbolt",
    "Warranty": "3 Years"
  },
  {
    "Full Product Name": "Dell UltraSharp 27 4K Thunderbolt Hub Monitor - U2725QE",
    "Model": "U2725QE",
    "Brand": "DELL",
    "Brief Naming": "Dell UltraSharp Series LED Monitor",
    "Size": "27\"",
    "Resolution": "3840 x 2160 4K UHD",
    "Response Time": "",
    "Refresh Rate": "120Hz",
    "Compatible Ports": "DisplayPort, HDMI, USB-C, Thunderbolt, Ethernet",
    "Warranty": "3 Years"
  },
  {
    "Full Product Name": "Alienware 27 280Hz QD-OLED Gaming Monitor - AW2725D",
    "Model": "AW2725D",
    "Brand": "DELL",
    "Brief Naming": "Dell Alienware Series LED Monitor",
    "Size": "27\"",
    "Resolution": "2560 x 1440 QHD",
    "Response Time": "",
    "Refresh Rate": "280Hz",
    "Compatible Ports": "DisplayPort, HDMI, USB-C, Thunderbolt",
    "Warranty": "3 Years"
  },
  {
    "Full Product Name": "Dell 32 Plus 4K Monitor - S3225QS",
    "Model": "S3225QS",
    "Brand": "DELL",
    "Brief Naming": "DELL S Series LED Monitor",
    "Size": "32\"",
    "Resolution": "3840 x 2160 4K UHD",
    "Response Time": "5.0ms",
    "Refresh Rate": "120Hz",
    "Compatible Ports": "2 HDMI, 1 DisplayPort",
    "Warranty": "3 Years"
  },
  {
    "Full Product Name": "Dell 22 Monitor - SE2225HM",
    "Model": "SE2225HM",
    "Brand": "DELL",
    "Brief Naming": "DELL SE Series LED Monitor",
    "Size": "21.5 Inch",
    "Resolution": "1920 x 1080 FHD",
    "Response Time": "8.0ms",
    "Refresh Rate": "100Hz",
    "Compatible Ports": "1 HDMI (HDCP 1.4), 1 VGA",
    "Warranty": "3 Years"
  },
  {
    "Full Product Name": "Dell 27 Plus 4K Monitor - S2725QS",
    "Model": "S2725QS",
    "Brand": "DELL",
    "Brief Naming": "DELL S Series LED Monitor",
    "Size": "27\"",
    "Resolution": "3840 x 2160 4K UHD",
    "Response Time": "8.0ms",
    "Refresh Rate": "120Hz",
    "Compatible Ports": "2 HDMI, 1 DisplayPort",
    "Warranty": "3 Years"
  },
  {
    "Full Product Name": "Alienware 27 360Hz QD-OLED Gaming Monitor - AW2725DF",
    "Model": "AW2725DF",
    "Brand": "DELL",
    "Brief Naming": "Dell Alienware Series LED Monitor",
    "Size": "27\"",
    "Resolution": "2560 x 1440 QHD",
    "Response Time": "",
    "Refresh Rate": "360Hz",
    "Compatible Ports": "DisplayPort, HDMI, USB-C, Thunderbolt",
    "Warranty": "3 Years"
  },
  {
    "Full Product Name": "Dell 34 Plus USB-C Monitor - S3425DW",
    "Model": "S3425DW",
    "Brand": "DELL",
    "Brief Naming": "DELL S Series LED Monitor",
    "Size": "34\"",
    "Resolution": "3440 x 1440 UWQHD",
    "Response Time": "1.0ms",
    "Refresh Rate": "120Hz",
    "Compatible Ports": "2 HDMI, 1 DisplayPort",
    "Warranty": "3 Years"
  },
  {
    "Full Product Name": "Dell 32 Plus 4K QD-OLED Monitor - S3225QC",
    "Model": "S3225QC",
    "Brand": "DELL",
    "Brief Naming": "DELL S Series LED Monitor",
    "Size": "32\"",
    "Resolution": "3840 x 2160 4K UHD",
    "Response Time": "",
    "Refresh Rate": "120Hz",
    "Compatible Ports": "1 HDMI, 1 DisplayPort, 1 USB-C",
    "Warranty": "3 Years"
  },
  {
    "Full Product Name": "Dell Pro 24 Adjustable Stand Monitor - E2425HSM",
    "Model": "E2425HS",
    "Brand": "DELL",
    "Brief Naming": "DELL E Series LED Monitor",
    "Size": "24\"",
    "Resolution": "",
    "Response Time": "5.0ms",
    "Refresh Rate": "100Hz",
    "Compatible Ports": "1 HDMI, 1 DisplayPort, 1 VGA",
    "Warranty": "3 Years"
  },
  {
    "Full Product Name": "Dell Pro 24 Plus QHD Monitor - P2425D",
    "Model": "P2425D",
    "Brand": "DELL",
    "Brief Naming": "DELL Pro Series LED Monitor",
    "Size": "24\"",
    "Resolution": "2560 x 1440 QHD",
    "Response Time": "8.0ms",
    "Refresh Rate": "100Hz",
    "Compatible Ports": "1 HDMI, 1 DisplayPort, 1 USB-C",
    "Warranty": "3 Years"
  },
  {
    "Full Product Name": "Alienware 34 240Hz QD-OLED Gaming Monitor - AW3425DW",
    "Model": "AW3425DW",
    "Brand": "DELL",
    "Brief Naming": "Dell Alienware Series LED Monitor",
    "Size": "34\"",
    "Resolution": "2560 x 1440 QHD",
    "Response Time": "",
    "Refresh Rate": "240Hz",
    "Compatible Ports": "DisplayPort, HDMI, USB-C, Thunderbolt",
    "Warranty": "3 Years"
  },
  {
    "Full Product Name": "Dell Pro 32 Plus 4K USB-C Hub Monitor - P3225QE",
    "Model": "P3225QE",
    "Brand": "DELL",
    "Brief Naming": "DELL Pro Series LED Monitor",
    "Size": "32\"",
    "Resolution": "3840 x 2160 4K UHD",
    "Response Time": "8.0ms",
    "Refresh Rate": "100Hz",
    "Compatible Ports": "1 HDMI, 1 DisplayPort, 1 USB-C",
    "Warranty": "3 Years"
  },
  {
    "Full Product Name": "Dell Pro 24 Monitor - E2425HM",
    "Model": "E2425HM",
    "Brand": "DELL",
    "Brief Naming": "DELL E Series LED Monitor",
    "Size": "24\"",
    "Resolution": "",
    "Response Time": "8.0ms",
    "Refresh Rate": "100Hz",
    "Compatible Ports": "1 HDMI, 1 DisplayPort, 1 VGA",
    "Warranty": "3 Years"
  },
  {
    "Full Product Name": "Dell Pro 27 Plus QHD USB-C Hub Monitor - P2725DE",
    "Model": "P2725DE",
    "Brand": "DELL",
    "Brief Naming": "DELL Pro Series LED Monitor",
    "Size": "27\"",
    "Resolution": "2560 x 1440 QHD",
    "Response Time": "5.0ms",
    "Refresh Rate": "100Hz",
    "Compatible Ports": "1 HDMI, 1 DisplayPort, 1 USB-C",
    "Warranty": "3 Years"
  },
  {
    "Full Product Name": "Dell 27 200Hz Monitor - SE2725HG",
    "Model": "SE2725HG",
    "Brand": "DELL",
    "Brief Naming": "DELL SE Series LED Monitor",
    "Size": "27\"",
    "Resolution": "1920 x 1080 FHD",
    "Response Time": "1.0ms",
    "Refresh Rate": "200Hz",
    "Compatible Ports": "2 HDMI, 1 DisplayPort",
    "Warranty": "3 Years"
  },
  {
    "Full Product Name": "Dell UltraSharp 27 Monitor - U2724D",
    "Model": "U2724D",
    "Brand": "DELL",
    "Brief Naming": "Dell UltraSharp Series LED Monitor",
    "Size": "27\"",
    "Resolution": "2560 x 1440 QHD",
    "Response Time": "8.0ms",
    "Refresh Rate": "120Hz",
    "Compatible Ports": "DisplayPort, HDMI, USB-C, Thunderbolt",
    "Warranty": "3 Years"
  },
  {
    "Full Product Name": "Dell UltraSharp 32 4K Thunderbolt Hub Monitor - U3225QE",
    "Model": "U3225QE",
    "Brand": "DELL",
    "Brief Naming": "Dell UltraSharp Series LED Monitor",
    "Size": "32\"",
    "Resolution": "3840 x 2160 4K UHD",
    "Response Time": "",
    "Refresh Rate": "120Hz",
    "Compatible Ports": "DisplayPort, HDMI, USB-C, Thunderbolt, Ethernet",
    "Warranty": "3 Years"
  },
  {
    "Full Product Name": "Alienware 27 4K QD-OLED Gaming Monitor - AW2725Q",
    "Model": "AW2725Q",
    "Brand": "DELL",
    "Brief Naming": "Dell Alienware Series LED Monitor",
    "Size": "27\"",
    "Resolution": "2560 x 1440 QHD",
    "Response Time": "",
    "Refresh Rate": "240Hz",
    "Compatible Ports": "DisplayPort, HDMI, USB-C, Thunderbolt",
    "Warranty": "3 Years"
  },
  {
    "Full Product Name": "Alienware 25 320Hz Gaming Monitor - AW2525HM",
    "Model": "AW2525HM",
    "Brand": "DELL",
    "Brief Naming": "Dell Alienware Series LED Monitor",
    "Size": "25\"",
    "Resolution": "1920 x 1080 FHD",
    "Response Time": "1.0ms",
    "Refresh Rate": "320Hz",
    "Compatible Ports": "DisplayPort, HDMI, USB-C, Thunderbolt",
    "Warranty": "3 Years"
  },
  {
    "Full Product Name": "Dell Pro 22 Monitor - E2225HM",
    "Model": "E2225HM",
    "Brand": "DELL",
    "Brief Naming": "DELL E Series LED Monitor",
    "Size": "22\"",
    "Resolution": "",
    "Response Time": "5.0ms",
    "Refresh Rate": "100Hz",
    "Compatible Ports": "1 HDMI, 1 DisplayPort, 1 VGA",
    "Warranty": "3 Years"
  },
  {
    "Full Product Name": "Dell 27 Plus Monitor - S2725HSM​",
    "Model": "S2725HS",
    "Brand": "DELL",
    "Brief Naming": "DELL S Series LED Monitor",
    "Size": "27\"",
    "Resolution": "",
    "Response Time": "1.0ms",
    "Refresh Rate": "144Hz",
    "Compatible Ports": "2 HDMI",
    "Warranty": "3 Years"
  },
  {
    "Full Product Name": "Dell Pro 27 Plus QHD Monitor - P2725D",
    "Model": "P2725D",
    "Brand": "DELL",
    "Brief Naming": "DELL Pro Series LED Monitor",
    "Size": "27\"",
    "Resolution": "2560 x 1440 QHD",
    "Response Time": "5.0ms",
    "Refresh Rate": "100Hz",
    "Compatible Ports": "1 HDMI, 1 DisplayPort, 1 USB-C",
    "Warranty": "3 Years"
  },
  {
    "Full Product Name": "Dell Pro 34 Plus USB-C Hub Monitor - P3425WE",
    "Model": "P3425WE",
    "Brand": "DELL",
    "Brief Naming": "DELL Pro Series LED Monitor",
    "Size": "34\"",
    "Resolution": "",
    "Response Time": "5.0ms",
    "Refresh Rate": "",
    "Compatible Ports": "1 HDMI, 1 DisplayPort, 1 USB-C",
    "Warranty": "3 Years"
  },
  {
    "Full Product Name": "Dell Pro 27 Plus 4K USB-C Hub Monitor - P2725QE",
    "Model": "P2725QE",
    "Brand": "DELL",
    "Brief Naming": "DELL Pro Series LED Monitor",
    "Size": "27\"",
    "Resolution": "3840 x 2160 4K UHD",
    "Response Time": "8.0ms",
    "Refresh Rate": "100Hz",
    "Compatible Ports": "1 HDMI, 1 DisplayPort, 1 USB-C",
    "Warranty": "3 Years"
  },
  {
    "Full Product Name": "Dell Pro 22 Adjustable Stand Monitor - E2225HSM",
    "Model": "E2225HS",
    "Brand": "DELL",
    "Brief Naming": "DELL E Series LED Monitor",
    "Size": "22\"",
    "Resolution": "",
    "Response Time": "5.0ms",
    "Refresh Rate": "100Hz",
    "Compatible Ports": "1 HDMI, 1 DisplayPort, 1 VGA",
    "Warranty": "3 Years"
  },
  {
    "Full Product Name": "Dell Pro 27 Monitor - E2725HM",
    "Model": "E2725HM",
    "Brand": "DELL",
    "Brief Naming": "DELL E Series LED Monitor",
    "Size": "27\"",
    "Resolution": "",
    "Response Time": "8.0ms",
    "Refresh Rate": "100Hz",
    "Compatible Ports": "1 HDMI, 1 DisplayPort, 1 VGA",
    "Warranty": "3 Years"
  },
  {
    "Full Product Name": "Alienware 27 QHD Gaming Monitor - AW2725DM",
    "Model": "AW2725DM",
    "Brand": "DELL",
    "Brief Naming": "Dell Alienware Series LED Monitor",
    "Size": "27\"",
    "Resolution": "2560 x 1440 QHD",
    "Response Time": "2.0ms",
    "Refresh Rate": "180Hz",
    "Compatible Ports": "DisplayPort, HDMI, USB-C, Thunderbolt",
    "Warranty": "3 Years"
  },
  {
    "Full Product Name": "Dell UltraSharp 27 Thunderbolt™ Hub Monitor - U2724DE",
    "Model": "U2724DE",
    "Brand": "DELL",
    "Brief Naming": "Dell UltraSharp Series LED Monitor",
    "Size": "27\"",
    "Resolution": "2560 x 1440 QHD",
    "Response Time": "8.0ms",
    "Refresh Rate": "120Hz",
    "Compatible Ports": "DisplayPort, HDMI, USB-C, Thunderbolt, Ethernet",
    "Warranty": "3 Years"
  },
  {
    "Full Product Name": "Dell UltraSharp 34 Curved Thunderbolt™  Hub Monitor - U3425WE",
    "Model": "U3425WE",
    "Brand": "DELL",
    "Brief Naming": "Dell UltraSharp Series LED Monitor",
    "Size": "34\"",
    "Resolution": "",
    "Response Time": "8.0ms",
    "Refresh Rate": "120Hz",
    "Compatible Ports": "DisplayPort, HDMI, USB-C, Thunderbolt, Ethernet",
    "Warranty": "3 Years"
  },
  {
    "Full Product Name": "Dell Pro 24 Plus QHD USB-C Hub Monitor - P2425DE",
    "Model": "P2425DE",
    "Brand": "DELL",
    "Brief Naming": "DELL Pro Series LED Monitor",
    "Size": "24\"",
    "Resolution": "2560 x 1440 QHD",
    "Response Time": "8.0ms",
    "Refresh Rate": "100Hz",
    "Compatible Ports": "1 HDMI, 1 DisplayPort, 1 USB-C",
    "Warranty": "3 Years"
  },
  {
    "Full Product Name": "Dell 27 Plus QHD USB-C Monitor - S2725DC",
    "Model": "S2725DC",
    "Brand": "DELL",
    "Brief Naming": "DELL S Series LED Monitor",
    "Size": "27\"",
    "Resolution": "2560 x 1440 QHD",
    "Response Time": "1.0ms",
    "Refresh Rate": "144Hz",
    "Compatible Ports": "1 HDMI, 1 DisplayPort, 1 USB-C",
    "Warranty": "3 Years"
  },
  {
    "Full Product Name": "Dell UltraSharp 38 Curved USB-C Hub Monitor - U3824DW",
    "Model": "U3824DW",
    "Brand": "DELL",
    "Brief Naming": "Dell UltraSharp Series LED Monitor",
    "Size": "38\"",
    "Resolution": "3840 x 1600",
    "Response Time": "5.0ms",
    "Refresh Rate": "",
    "Compatible Ports": "DisplayPort, HDMI, USB-C, Thunderbolt, Ethernet",
    "Warranty": "3 Years"
  },
  {
    "Full Product Name": "Dell 24 Plus Monitor - S2425HSM",
    "Model": "S2425HS",
    "Brand": "DELL",
    "Brief Naming": "DELL S Series LED Monitor",
    "Size": "24\"",
    "Resolution": "",
    "Response Time": "1.0ms",
    "Refresh Rate": "144Hz",
    "Compatible Ports": "2 HDMI",
    "Warranty": "3 Years"
  },
  {
    "Full Product Name": "Dell 24 240Hz Adjustable Stand Monitor - SE2426HGS",
    "Model": "SE2426HG",
    "Brand": "DELL",
    "Brief Naming": "DELL SE Series LED Monitor",
    "Size": "24\"",
    "Resolution": "1920 x 1080 FHD",
    "Response Time": "0.5ms",
    "Refresh Rate": "240Hz",
    "Compatible Ports": "2 HDMI, 1 DisplayPort",
    "Warranty": "3 Years"
  },
  {
    "Full Product Name": "Dell Pro 27 Adjustable Stand Monitor - E2726HS​",
    "Model": "E2726HS",
    "Brand": "DELL",
    "Brief Naming": "DELL E Series LED Monitor",
    "Size": "27\"",
    "Resolution": "",
    "Response Time": "5.0ms",
    "Refresh Rate": "100Hz",
    "Compatible Ports": "1 HDMI, 1 DisplayPort, 1 VGA",
    "Warranty": "3 Years"
  },
  {
    "Full Product Name": "Dell Pro 34 Plus Video Conferencing Monitor - P3424WEB",
    "Model": "P3424WE",
    "Brand": "DELL",
    "Brief Naming": "DELL Pro Series LED Monitor",
    "Size": "34\"",
    "Resolution": "3440 x 1440 UWQHD",
    "Response Time": "5.0ms",
    "Refresh Rate": "",
    "Compatible Ports": "1 HDMI, 1 USB-C",
    "Warranty": "3 Years"
  },
  {
    "Full Product Name": "Dell Pro 27 QHD Monitor - E2726DS",
    "Model": "E2726DS",
    "Brand": "DELL",
    "Brief Naming": "DELL E Series LED Monitor",
    "Size": "27\"",
    "Resolution": "2560 x 1440 QHD",
    "Response Time": "5.0ms",
    "Refresh Rate": "100Hz",
    "Compatible Ports": "1 HDMI, 1 DisplayPort",
    "Warranty": "3 Years"
  },
  {
    "Full Product Name": "Dell 27 Plus QHD Monitor - S2725DSM",
    "Model": "S2725DS",
    "Brand": "DELL",
    "Brief Naming": "DELL S Series LED Monitor",
    "Size": "27\"",
    "Resolution": "2560 x 1440 QHD",
    "Response Time": "1.0ms",
    "Refresh Rate": "144Hz",
    "Compatible Ports": "2 HDMI, 1 DisplayPort",
    "Warranty": "3 Years"
  },
  {
    "Full Product Name": "Dell Pro P 24 16:10 USB-C Hub Monitor - P2426E",
    "Model": "P2426E",
    "Brand": "DELL",
    "Brief Naming": "DELL Pro Series LED Monitor",
    "Size": "24\"",
    "Resolution": "",
    "Response Time": "5.0ms",
    "Refresh Rate": "100Hz",
    "Compatible Ports": "1 HDMI, 1 DisplayPort, USB-C",
    "Warranty": "3 Years"
  },
  {
    "Full Product Name": "Dell 24 Monitor - SE2426H",
    "Model": "SE2426H",
    "Brand": "DELL",
    "Brief Naming": "DELL SE Series LED Monitor",
    "Size": "24\"",
    "Resolution": "1920 x 1080 FHD",
    "Response Time": "8.0ms",
    "Refresh Rate": "144Hz",
    "Compatible Ports": "1 HDMI (HDCP 1.4), 1 VGA",
    "Warranty": "3 Years"
  },
  {
    "Full Product Name": "Dell 24 240Hz Monitor - SE2426HG",
    "Model": "SE2426HG",
    "Brand": "DELL",
    "Brief Naming": "DELL SE Series LED Monitor",
    "Size": "24\"",
    "Resolution": "1920 x 1080 FHD",
    "Response Time": "0.5ms",
    "Refresh Rate": "240Hz",
    "Compatible Ports": "2 HDMI, 1 DisplayPort",
    "Warranty": "3 Years"
  },
  {
    "Full Product Name": "Dell 27 Monitor - SE2726H",
    "Model": "SE2726H",
    "Brand": "DELL",
    "Brief Naming": "DELL SE Series LED Monitor",
    "Size": "27\"",
    "Resolution": "1920 x 1080 FHD",
    "Response Time": "4.0ms",
    "Refresh Rate": "144Hz",
    "Compatible Ports": "2 HDMI, 1 DisplayPort",
    "Warranty": "3 Years"
  },
  {
    "Full Product Name": "Dell Pro P 22 Monitor - P2226H​",
    "Model": "P2226H",
    "Brand": "DELL",
    "Brief Naming": "DELL Pro Series LED Monitor",
    "Size": "22\"",
    "Resolution": "",
    "Response Time": "5.0ms",
    "Refresh Rate": "100Hz",
    "Compatible Ports": "1 HDMI, 1 DisplayPort, USB-C",
    "Warranty": "3 Years"
  },
  {
    "Full Product Name": "Dell Pro P 24 Monitor - P2426H​",
    "Model": "P2426H",
    "Brand": "DELL",
    "Brief Naming": "DELL Pro Series LED Monitor",
    "Size": "24\"",
    "Resolution": "",
    "Response Time": "5.0ms",
    "Refresh Rate": "120Hz",
    "Compatible Ports": "1 HDMI, 1 DisplayPort, USB-C",
    "Warranty": "3 Years"
  },
  {
    "Full Product Name": "Dell Pro 24 Video Conferencing Monitor - E2426HB​",
    "Model": "E2426HB",
    "Brand": "DELL",
    "Brief Naming": "DELL E Series LED Monitor",
    "Size": "24\"",
    "Resolution": "",
    "Response Time": "5.0ms",
    "Refresh Rate": "120Hz",
    "Compatible Ports": "1 HDMI, 1 DisplayPort",
    "Warranty": "3 Years"
  },
  {
    "Full Product Name": "Dell Pro P 24 16:10 Monitor - P2426",
    "Model": "P2426",
    "Brand": "DELL",
    "Brief Naming": "DELL Pro Series LED Monitor",
    "Size": "24\"",
    "Resolution": "",
    "Response Time": "5.0ms",
    "Refresh Rate": "100Hz",
    "Compatible Ports": "1 HDMI, 1 DisplayPort, USB-C",
    "Warranty": "3 Years"
  },
  {
    "Full Product Name": "Dell Pro P 27 Monitor - P2726H​",
    "Model": "P2726H",
    "Brand": "DELL",
    "Brief Naming": "DELL Pro Series LED Monitor",
    "Size": "27\"",
    "Resolution": "",
    "Response Time": "5.0ms",
    "Refresh Rate": "120Hz",
    "Compatible Ports": "1 HDMI, 1 DisplayPort, USB-C",
    "Warranty": "3 Years"
  },
  {
    "Full Product Name": "Dell UltraSharp 43 4K USB-C Hub Monitor - U4323QE",
    "Model": "U4323QE",
    "Brand": "DELL",
    "Brief Naming": "Dell UltraSharp Series LED Monitor",
    "Size": "43\"",
    "Resolution": "3840 x 2160 4K UHD",
    "Response Time": "5.0ms",
    "Refresh Rate": "",
    "Compatible Ports": "DisplayPort, HDMI, USB-C, Thunderbolt, Ethernet",
    "Warranty": "3 Years"
  },
  {
    "Full Product Name": "Alienware 27 4K Dual-Resolution Gaming Monitor - AW2725QF",
    "Model": "AW2725QF",
    "Brand": "DELL",
    "Brief Naming": "Dell Alienware Series LED Monitor",
    "Size": "27\"",
    "Resolution": "2560 x 1440 QHD",
    "Response Time": "0.5ms",
    "Refresh Rate": "180Hz",
    "Compatible Ports": "DisplayPort, HDMI, USB-C, Thunderbolt",
    "Warranty": "3 Years"
  },
  {
    "Full Product Name": "Dell Pro P 24 USB-C Hub Monitor - P2426HE",
    "Model": "P2426HE",
    "Brand": "DELL",
    "Brief Naming": "DELL Pro Series LED Monitor",
    "Size": "24\"",
    "Resolution": "",
    "Response Time": "5.0ms",
    "Refresh Rate": "120Hz",
    "Compatible Ports": "1 HDMI, 2 DisplayPort (1 in, 1 out), USB-C",
    "Warranty": "3 Years"
  },
  {
    "Full Product Name": "Dell UltraSharp 49 Curved USB-C Hub Monitor - U4924DW",
    "Model": "U4924DW",
    "Brand": "DELL",
    "Brief Naming": "Dell UltraSharp Series LED Monitor",
    "Size": "49\"",
    "Resolution": "5120 x 1440",
    "Response Time": "",
    "Refresh Rate": "",
    "Compatible Ports": "DisplayPort, HDMI, USB-C, Thunderbolt",
    "Warranty": "3 Years"
  },
  {
    "Full Product Name": "Dell Pro P 27 USB-C Hub Monitor - P2726HE",
    "Model": "P2726HE",
    "Brand": "DELL",
    "Brief Naming": "DELL Pro Series LED Monitor",
    "Size": "27\"",
    "Resolution": "",
    "Response Time": "5.0ms",
    "Refresh Rate": "120Hz",
    "Compatible Ports": "1 HDMI, 2 DisplayPort (1 in, 1 out), USB-C",
    "Warranty": "3 Years"
  },
  {
    "Full Product Name": "Alienware 27 240Hz QD-OLED Gaming Monitor - AW2726DM",
    "Model": "AW2726DM",
    "Brand": "DELL",
    "Brief Naming": "Dell Alienware Series LED Monitor",
    "Size": "27\"",
    "Resolution": "2560 x 1440 QHD",
    "Response Time": "",
    "Refresh Rate": "240Hz",
    "Compatible Ports": "DisplayPort, HDMI, USB-C, Thunderbolt",
    "Warranty": "3 Years"
  },
  {
    "Full Product Name": "Dell UltraSharp 52 Thunderbolt Hub Monitor - U5226KW",
    "Model": "U5226KW",
    "Brand": "DELL",
    "Brief Naming": "Dell UltraSharp Series LED Monitor",
    "Size": "52\"",
    "Resolution": "",
    "Response Time": "",
    "Refresh Rate": "120Hz",
    "Compatible Ports": "DisplayPort, HDMI, USB-C, Thunderbolt, Ethernet",
    "Warranty": "3 Years"
  },
  {
    "Full Product Name": "Dell 27 Monitor - SE2725HM",
    "Model": "SE2725HM",
    "Brand": "DELL",
    "Brief Naming": "DELL SE Series LED Monitor",
    "Size": "27\"",
    "Resolution": "1920 x 1080 FHD",
    "Response Time": "5.0ms",
    "Refresh Rate": "100Hz",
    "Compatible Ports": "1 HDMI (HDCP 1.4), 1 VGA",
    "Warranty": "3 Years"
  },
  {
    "Full Product Name": "Dell Pro 27 Plus Monitor - P2725H",
    "Model": "P2725H",
    "Brand": "DELL",
    "Brief Naming": "DELL Pro Series LED Monitor",
    "Size": "27\"",
    "Resolution": "1920 x 1080 FHD",
    "Response Time": "5.0ms",
    "Refresh Rate": "100Hz",
    "Compatible Ports": "1 HDMI, 1 VGA, 1 USB-C",
    "Warranty": "3 Years"
  },
  {
    "Full Product Name": "Dell Pro 24 Plus USB-C Hub Monitor - P2425HE",
    "Model": "P2425HE",
    "Brand": "DELL",
    "Brief Naming": "DELL Pro Series LED Monitor",
    "Size": "24\"",
    "Resolution": "1920 x 1200 WUXGA",
    "Response Time": "5.0ms",
    "Refresh Rate": "100Hz",
    "Compatible Ports": "1 HDMI, 1 USB-C",
    "Warranty": "3 Years"
  },
  {
    "Full Product Name": "Alienware 34 Gaming Monitor - AW3425DWM",
    "Model": "AW3425DW",
    "Brand": "DELL",
    "Brief Naming": "Dell Alienware Series LED Monitor",
    "Size": "34\"",
    "Resolution": "2560 x 1440 QHD",
    "Response Time": "1.0ms",
    "Refresh Rate": "180Hz",
    "Compatible Ports": "DisplayPort, HDMI, USB-C, Thunderbolt",
    "Warranty": "3 Years"
  },
  {
    "Full Product Name": "Dell Pro 24 Plus 16:10 Monitor - P2425",
    "Model": "P2425",
    "Brand": "DELL",
    "Brief Naming": "DELL Pro Series LED Monitor",
    "Size": "24\"",
    "Resolution": "1920 x 1200 WUXGA",
    "Response Time": "5.0ms",
    "Refresh Rate": "100Hz",
    "Compatible Ports": "1 HDMI, 1 VGA, 1 USB-C",
    "Warranty": "3 Years"
  },
  {
    "Full Product Name": "Dell Pro 24 Plus 16:10 USB-C Hub Monitor - P2425E",
    "Model": "P2425E",
    "Brand": "DELL",
    "Brief Naming": "DELL Pro Series LED Monitor",
    "Size": "24\"",
    "Resolution": "1920 x 1200 WUXGA",
    "Response Time": "5.0ms",
    "Refresh Rate": "100Hz",
    "Compatible Ports": "1 HDMI, 1 DisplayPort, 1 USB-C",
    "Warranty": "3 Years"
  },
  {
    "Full Product Name": "Dell UltraSharp 32 6K Monitor - U3224KB",
    "Model": "U3224KB",
    "Brand": "DELL",
    "Brief Naming": "Dell UltraSharp Series LED Monitor",
    "Size": "32\"",
    "Resolution": "3840 x 2160 4K UHD",
    "Response Time": "",
    "Refresh Rate": "",
    "Compatible Ports": "DisplayPort, HDMI, USB-C, Thunderbolt, Ethernet",
    "Warranty": "3 Years"
  },
  {
    "Model": "U2424H",
    "Full Product Name": "Dell UltraSharp 24 USB-C Hub Monitor - U2424H",
    "Brand": "DELL",
    "Brief Naming": "Dell UltraSharp Series LED Monitor",
    "Size": "24\"",
    "Resolution": "1920 x 1080 FHD",
    "Response Time": "8.0ms",
    "Refresh Rate": "120Hz",
    "Compatible Ports": "DisplayPort, HDMI, USB-C, Thunderbolt, Ethernet",
    "Warranty": "3 Years"
  },
  {
    "Full Product Name": "DELL Monitor - TEST12345",
    "Model": "TEST12345",
    "Brand": "DELL",
    "Brief Naming": "Dell Monitor",
    "Size": "\"\"",
    "Resolution": "",
    "Response Time": "",
    "Refresh Rate": "",
    "Compatible Ports": "",
    "Warranty": ""
  },
  {
    "Full Product Name": "DELL Monitor - SE2425HM",
    "Model": "SE2425HM",
    "Brand": "DELL",
    "Brief Naming": "DELL SE Series LED Monitor",
    "Size": "\"23.8 Inch\"",
    "Resolution": "1920 x 1080 FHD",
    "Response Time": "5ms",
    "Refresh Rate": "100 Hz",
    "Compatible Ports": "1 HDMI (HDCP 1.4), 1 VGA",
    "Warranty": "3 Years"
  },
  {
    "Full Product Name": "DELL Monitor - SE2425HG",
    "Model": "SE2425HG",
    "Brand": "DELL",
    "Brief Naming": "DELL SE Series LED Monitor",
    "Size": "\"23.8 Inch\"",
    "Resolution": "1920 x 1080 FHD",
    "Response Time": "1ms",
    "Refresh Rate": "200Hz",
    "Compatible Ports": "2 HDMI ports, 1 DisplayPort 1.4, 1 Headphone-out port (3.5 mm jack)",
    "Warranty": "3 Year"
  },
  {
    "Full Product Name": "Dell 27 USB-C Hub Monitor - P2722HE",
    "Model": "P2722HE",
    "Brand": "DELL",
    "Brief Naming": "DELL Pro Series LED Monitor",
    "Size": "27 Inch",
    "Resolution": "1920 x 1080 FHD",
    "Response Time": "5ms",
    "Refresh Rate": "60Hz",
    "Compatible Ports": "1 HDMI, 1 DisplayPort, 1 DisplayPort Out (MST), 1 USB-C (65W Power Delivery), 4 USB Type-A, 1 RJ-45 Ethernet, Audio Out",
    "Warranty": "3 Years"
  }
]